bbaug/__init__.py
bbaug/_version.py
bbaug/exceptions.py
bbaug/augmentations/__init__.py
bbaug/augmentations/augmentations.py
bbaug/policies/__init__.py
bbaug/policies/policies.py
bbaug/visuals/__init__.py
bbaug/visuals/visuals.py
bbaug-0.4.2.dist-info/LICENSE
bbaug-0.4.2.dist-info/METADATA
bbaug-0.4.2.dist-info/WHEEL
bbaug-0.4.2.dist-info/top_level.txt
bbaug-0.4.2.dist-info/RECORD
