Metadata-Version: 2.1
Name: bbaug
Version: 0.4.2
Summary: Bounding box augmentation for PyTorch with Google's Brain Team augmentation policies
Home-page: https://github.com/harpalsahota/bbaug
Author: Harpal Sahota
Author-email: harpal28sahota@gmail.com
License: UNKNOWN
Platform: UNKNOWN
Classifier: Development Status :: 4 - Beta
Classifier: License :: OSI Approved :: MIT License
Classifier: Operating System :: OS Independent
Classifier: Programming Language :: Python
Classifier: Programming Language :: Python :: 3
Classifier: Programming Language :: Python :: 3.5
Classifier: Programming Language :: Python :: 3.6
Classifier: Programming Language :: Python :: 3.7
Classifier: Programming Language :: Python :: 3.8
Classifier: Programming Language :: Python :: 3 :: Only
Classifier: Topic :: Scientific/Engineering :: Image Recognition
Requires-Python: >=3.5
Requires-Dist: imgaug
